anaconda_cloud_auth/__init__.py
anaconda_cloud_auth/__main__.py
anaconda_cloud_auth/_version.py
anaconda_cloud_auth/actions.py
anaconda_cloud_auth/cli.py
anaconda_cloud_auth/client.py
anaconda_cloud_auth/config.py
anaconda_cloud_auth/exceptions.py
anaconda_cloud_auth/handlers.py
anaconda_cloud_auth/panel.py
anaconda_cloud_auth/py.typed
anaconda_cloud_auth/token.py
anaconda_cloud_auth/_conda/__init__.py
anaconda_cloud_auth/_conda/auth_handler.py
anaconda_cloud_auth/_conda/entrypoint.py
anaconda_cloud_auth/_conda/plugins.py
anaconda_cloud_auth-0.7.2.dist-info/METADATA
anaconda_cloud_auth-0.7.2.dist-info/WHEEL
anaconda_cloud_auth-0.7.2.dist-info/entry_points.txt
anaconda_cloud_auth-0.7.2.dist-info/licenses/LICENSE
anaconda_cloud_auth-0.7.2.dist-info/RECORD
