Metadata-Version: 2.3
Name: anaconda-cloud-auth
Version: 0.7.2
Summary: A client auth library for Anaconda.cloud APIs
License: BSD-3-Clause
License-File: LICENSE
Requires-Python: >=3.8
Requires-Dist: anaconda-cli-base>=0.4.0
Requires-Dist: cryptography>=3.4.0
Requires-Dist: keyring
Requires-Dist: pkce
Requires-Dist: pydantic
Requires-Dist: pyjwt
Requires-Dist: python-dotenv
Requires-Dist: requests
Requires-Dist: semver<4
Provides-Extra: dev
Requires-Dist: mypy; extra == 'dev'
Requires-Dist: pytest; extra == 'dev'
Requires-Dist: pytest-cov; extra == 'dev'
Requires-Dist: pytest-mock; extra == 'dev'
Requires-Dist: responses; extra == 'dev'
Requires-Dist: tox; extra == 'dev'
Requires-Dist: types-requests; extra == 'dev'
Provides-Extra: publish
Requires-Dist: build; extra == 'publish'
Requires-Dist: twine; extra == 'publish'
Requires-Dist: wheel; extra == 'publish'
